symphony_data_map/__init__.py
symphony_data_map/_default_codes.py
symphony_data_map/_frontend.py
symphony_data_map/_version.py
symphony_data_map/widget.py
symphony_data_map/labextension/build_log.json
symphony_data_map/labextension/package.json
symphony_data_map/labextension/static/lib_index_js.64f227db515b6c7f3c95.js
symphony_data_map/labextension/static/lib_index_js.64f227db515b6c7f3c95.js.map
symphony_data_map/labextension/static/lib_index_js.dddbbc113c8b908251e9.js
symphony_data_map/labextension/static/lib_index_js.dddbbc113c8b908251e9.js.map
symphony_data_map/labextension/static/remoteEntry.159fc258a0b0d7e6b46e.js
symphony_data_map/labextension/static/remoteEntry.159fc258a0b0d7e6b46e.js.map
symphony_data_map/labextension/static/remoteEntry.b1011c15a2b00bc38101.js
symphony_data_map/labextension/static/remoteEntry.b1011c15a2b00bc38101.js.map
symphony_data_map/labextension/static/style.js
symphony_data_map/nbextension/extension.js
symphony_data_map/nbextension/index.js
symphony_data_map/standalone/widgets/SymphonyDataMap.js
symphony_data_map/standalone/widgets/SymphonyDataMap.js.map
symphony_data_map-1.0.2.data/data/etc/jupyter/nbconfig/notebook.d/symphony_data_map.json
symphony_data_map-1.0.2.data/data/share/jupyter/labextensions/symphony-data-map/build_log.json
symphony_data_map-1.0.2.data/data/share/jupyter/labextensions/symphony-data-map/install.json
symphony_data_map-1.0.2.data/data/share/jupyter/labextensions/symphony-data-map/package.json
symphony_data_map-1.0.2.data/data/share/jupyter/labextensions/symphony-data-map/static/lib_index_js.dddbbc113c8b908251e9.js
symphony_data_map-1.0.2.data/data/share/jupyter/labextensions/symphony-data-map/static/lib_index_js.dddbbc113c8b908251e9.js.map
symphony_data_map-1.0.2.data/data/share/jupyter/labextensions/symphony-data-map/static/remoteEntry.b1011c15a2b00bc38101.js
symphony_data_map-1.0.2.data/data/share/jupyter/labextensions/symphony-data-map/static/remoteEntry.b1011c15a2b00bc38101.js.map
symphony_data_map-1.0.2.dist-info/LICENSE.txt
symphony_data_map-1.0.2.dist-info/METADATA
symphony_data_map-1.0.2.dist-info/WHEEL
symphony_data_map-1.0.2.dist-info/top_level.txt
symphony_data_map-1.0.2.dist-info/RECORD
